{
  "id": "rec_1775297434902",
  "label": "y2",
  "started": "2026-04-04T15:40:34",
  "samples": [
    {
      "t": 91,
      "kind": "imu",
      "roll": -5.9,
      "pitch": -26.9,
      "yaw": 53.2
    },
    {
      "t": 211,
      "kind": "imu",
      "roll": -5.9,
      "pitch": -26.7,
      "yaw": 53.1
    },
    {
      "t": 330,
      "kind": "imu",
      "roll": -6.4,
      "pitch": -26.8,
      "yaw": 53.5
    },
    {
      "t": 451,
      "kind": "imu",
      "roll": -6.4,
      "pitch": -26.9,
      "yaw": 53.4
    },
    {
      "t": 572,
      "kind": "imu",
      "roll": -11.3,
      "pitch": -29.2,
      "yaw": 54.6
    },
    {
      "t": 692,
      "kind": "imu",
      "roll": -12.5,
      "pitch": -31.0,
      "yaw": 54.4
    },
    {
      "t": 812,
      "kind": "imu",
      "roll": -13.5,
      "pitch": -20.1,
      "yaw": 57.6
    },
    {
      "t": 932,
      "kind": "imu",
      "roll": -13.1,
      "pitch": -16.8,
      "yaw": 56.2
    },
    {
      "t": 1054,
      "kind": "imu",
      "roll": -15.8,
      "pitch": -31.4,
      "yaw": 51.8
    },
    {
      "t": 1231,
      "kind": "imu",
      "roll": -16.1,
      "pitch": -31.7,
      "yaw": 52.1
    },
    {
      "t": 1351,
      "kind": "imu",
      "roll": -13.4,
      "pitch": -11.4,
      "yaw": 53.7
    },
    {
      "t": 1471,
      "kind": "imu",
      "roll": -15.4,
      "pitch": 2.0,
      "yaw": 56.0
    },
    {
      "t": 1591,
      "kind": "gyro",
      "x": 0.141,
      "y": -1.021,
      "z": 0.7
    },
    {
      "t": 1711,
      "kind": "imu",
      "roll": -10.2,
      "pitch": -2.1,
      "yaw": 65.1
    },
    {
      "t": 1831,
      "kind": "gyro",
      "x": 0.805,
      "y": -2.445,
      "z": -2.0
    },
    {
      "t": 1952,
      "kind": "imu",
      "roll": 2.2,
      "pitch": -34.6,
      "yaw": 51.7
    },
    {
      "t": 2072,
      "kind": "gyro",
      "x": 0.068,
      "y": -0.139,
      "z": 0.0
    },
    {
      "t": 2192,
      "kind": "imu",
      "roll": 10.8,
      "pitch": -32.5,
      "yaw": 37.3
    },
    {
      "t": 2310,
      "kind": "gyro",
      "x": -0.084,
      "y": 0.006,
      "z": 0.0
    },
    {
      "t": 2430,
      "kind": "imu",
      "roll": 8.6,
      "pitch": -31.2,
      "yaw": 40.0
    },
    {
      "t": 2551,
      "kind": "gyro",
      "x": -0.02,
      "y": 0.135,
      "z": 0.0
    },
    {
      "t": 2672,
      "kind": "imu",
      "roll": 6.8,
      "pitch": -30.2,
      "yaw": 40.7
    },
    {
      "t": 2792,
      "kind": "gyro",
      "x": 0.051,
      "y": 0.045,
      "z": 0.07
    },
    {
      "t": 2911,
      "kind": "imu",
      "roll": 6.9,
      "pitch": -30.1,
      "yaw": 41.3
    },
    {
      "t": 3031,
      "kind": "gyro",
      "x": -0.025,
      "y": -0.018,
      "z": -0.0
    },
    {
      "t": 3151,
      "kind": "imu",
      "roll": 6.3,
      "pitch": -29.7,
      "yaw": 41.6
    },
    {
      "t": 3271,
      "kind": "gyro",
      "x": 0.023,
      "y": -0.006,
      "z": 0.0
    }
  ]
}