{
  "id": "rec_1775294880607",
  "label": "c",
  "started": "2026-04-04T14:58:00",
  "samples": [
    {
      "t": 94,
      "roll": 5.6,
      "pitch": -18.5,
      "yaw": 54.3
    },
    {
      "t": 214,
      "roll": 5.8,
      "pitch": -18.6,
      "yaw": 54.4
    },
    {
      "t": 334,
      "roll": 6.2,
      "pitch": -18.5,
      "yaw": 53.1
    },
    {
      "t": 453,
      "roll": 6.7,
      "pitch": -18.5,
      "yaw": 52.9
    },
    {
      "t": 573,
      "roll": 7.6,
      "pitch": -18.2,
      "yaw": 52.0
    },
    {
      "t": 754,
      "roll": 8.5,
      "pitch": -18.1,
      "yaw": 50.9
    },
    {
      "t": 874,
      "roll": 9.0,
      "pitch": -21.7,
      "yaw": 40.8
    },
    {
      "t": 993,
      "roll": -0.8,
      "pitch": -29.1,
      "yaw": 47.3
    },
    {
      "t": 1113,
      "roll": -16.1,
      "pitch": -20.4,
      "yaw": 79.7
    },
    {
      "t": 1354,
      "roll": -17.2,
      "pitch": -14.2,
      "yaw": 86.6
    },
    {
      "t": 1474,
      "roll": -9.8,
      "pitch": 2.7,
      "yaw": 94.0
    },
    {
      "t": 1593,
      "roll": 2.1,
      "pitch": 5.2,
      "yaw": 77.0
    },
    {
      "t": 1713,
      "roll": 2.1,
      "pitch": 5.2,
      "yaw": 7.0
    },
    {
      "t": 1834,
      "roll": 8.4,
      "pitch": -2.1,
      "yaw": 53.5
    },
    {
      "t": 1957,
      "roll": 9.8,
      "pitch": -4.9,
      "yaw": 49.7
    },
    {
      "t": 2074,
      "roll": 13.2,
      "pitch": -6.6,
      "yaw": 50.7
    },
    {
      "t": 2314,
      "roll": 13.0,
      "pitch": -6.4,
      "yaw": 50.4
    },
    {
      "t": 2434,
      "roll": 13.0,
      "pitch": -6.5,
      "yaw": 51.2
    },
    {
      "t": 2557,
      "roll": 12.7,
      "pitch": -6.3,
      "yaw": 51.6
    },
    {
      "t": 2677,
      "roll": 12.6,
      "pitch": -6.0,
      "yaw": 52.1
    },
    {
      "t": 2796,
      "roll": 12.5,
      "pitch": -6.0,
      "yaw": 52.2
    },
    {
      "t": 2914,
      "roll": 12.3,
      "pitch": -5.7,
      "yaw": 52.7
    },
    {
      "t": 3037,
      "roll": 12.4,
      "pitch": -5.8,
      "yaw": 52.9
    },
    {
      "t": 3154,
      "roll": 12.5,
      "pitch": -5.0,
      "yaw": 53.3
    }
  ]
}